CONTRIBUTING.rst
HISTORY.rst
LICENSE
MANIFEST.in
README.rst
setup.cfg
setup.py
docs/Makefile
docs/conf.py
docs/contributing.rst
docs/history.rst
docs/index.rst
docs/installation.rst
docs/make.bat
docs/readme.rst
docs/usage.rst
test_yapi1/__init__.py
test_yapi1/base.py
test_yapi1/cli.py
test_yapi1/group.py
test_yapi1/project.py
test_yapi1/test_yapi1.py
test_yapi1/user.py
test_yapi1.egg-info/PKG-INFO
test_yapi1.egg-info/SOURCES.txt
test_yapi1.egg-info/dependency_links.txt
test_yapi1.egg-info/entry_points.txt
test_yapi1.egg-info/not-zip-safe
test_yapi1.egg-info/requires.txt
test_yapi1.egg-info/top_level.txt
tests/__init__.py
tests/conftest.py
tests/test_group.py
tests/test_project.py
tests/test_test_yapi1.py
tests/test_user.py
tests/test_yapi_client.py