Metadata-Version: 2.1
Name: test-yapi1
Version: 0.1.0
Summary: 接口
Home-page: https://github.com/audreyr/test_yapi1
Author: wangshanshan
Author-email: a1249621536@163.com
License: MIT license
Keywords: test_yapi1
Platform: UNKNOWN
Classifier: Development Status :: 2 - Pre-Alpha
Classifier: Intended Audience :: Developers
Classifier: License :: OSI Approved :: MIT License
Classifier: Natural Language :: English
Classifier: Programming Language :: Python :: 3
Classifier: Programming Language :: Python :: 3.6
Classifier: Programming Language :: Python :: 3.7
Classifier: Programming Language :: Python :: 3.8
Requires-Python: >=3.6
License-File: LICENSE
